{
  "actions" : [ {
    "module" : "init",
    "date" : "2024-05-03T14:55:00.014306721Z",
    "properties" : {
      "projectName" : "Chips Project",
      "serverPort" : 8081,
      "baseName" : "gradleapp",
      "packageName" : "tech.jhipster.gradleapp",
      "jwtBase64Secret" : "NmE2NDhmMmQ5OWQzYzk4NmE4NjNlMmQzNmU3ZTU4ZDY2MmUxOWEwZGI4YTk4NDY0MTk4MmQyMWZlNDNlM2FjYg==",
      "date" : "2021-12-03T10:15:30.00Z",
      "kafkaClusterId" : "7870e9ec-dd1f-4562-86a2-df2199d5db1a",
      "springConfigurationFormat" : "yaml"
    }
  }, {
    "module" : "gradle-wrapper",
    "date" : "2024-05-03T14:55:00.083546269Z",
    "properties" : {
      "projectName" : "Chips Project",
      "serverPort" : 8081,
      "baseName" : "gradleapp",
      "packageName" : "tech.jhipster.gradleapp",
      "jwtBase64Secret" : "NmE2NDhmMmQ5OWQzYzk4NmE4NjNlMmQzNmU3ZTU4ZDY2MmUxOWEwZGI4YTk4NDY0MTk4MmQyMWZlNDNlM2FjYg==",
      "date" : "2021-12-03T10:15:30.00Z",
      "kafkaClusterId" : "7870e9ec-dd1f-4562-86a2-df2199d5db1a",
      "springConfigurationFormat" : "yaml"
    }
  }, {
    "module" : "gradle-java",
    "date" : "2024-05-03T14:55:00.161615525Z",
    "properties" : {
      "projectName" : "Chips Project",
      "serverPort" : 8081,
      "baseName" : "gradleapp",
      "packageName" : "tech.jhipster.gradleapp",
      "jwtBase64Secret" : "NmE2NDhmMmQ5OWQzYzk4NmE4NjNlMmQzNmU3ZTU4ZDY2MmUxOWEwZGI4YTk4NDY0MTk4MmQyMWZlNDNlM2FjYg==",
      "date" : "2021-12-03T10:15:30.00Z",
      "kafkaClusterId" : "7870e9ec-dd1f-4562-86a2-df2199d5db1a",
      "springConfigurationFormat" : "yaml"
    }
  }, {
    "module" : "sonar-qube-java-backend",
    "date" : "2024-05-03T14:55:00.223670668Z",
    "properties" : {
      "projectName" : "Chips Project",
      "serverPort" : 8081,
      "baseName" : "gradleapp",
      "packageName" : "tech.jhipster.gradleapp",
      "jwtBase64Secret" : "NmE2NDhmMmQ5OWQzYzk4NmE4NjNlMmQzNmU3ZTU4ZDY2MmUxOWEwZGI4YTk4NDY0MTk4MmQyMWZlNDNlM2FjYg==",
      "date" : "2021-12-03T10:15:30.00Z",
      "kafkaClusterId" : "7870e9ec-dd1f-4562-86a2-df2199d5db1a",
      "springConfigurationFormat" : "yaml"
    }
  }, {
    "module" : "github-actions-gradle",
    "date" : "2024-05-03T14:55:00.288689114Z",
    "properties" : {
      "projectName" : "Chips Project",
      "serverPort" : 8081,
      "baseName" : "gradleapp",
      "packageName" : "tech.jhipster.gradleapp",
      "jwtBase64Secret" : "NmE2NDhmMmQ5OWQzYzk4NmE4NjNlMmQzNmU3ZTU4ZDY2MmUxOWEwZGI4YTk4NDY0MTk4MmQyMWZlNDNlM2FjYg==",
      "date" : "2021-12-03T10:15:30.00Z",
      "kafkaClusterId" : "7870e9ec-dd1f-4562-86a2-df2199d5db1a",
      "springConfigurationFormat" : "yaml"
    }
  }, {
    "module" : "java-base",
    "date" : "2024-05-03T14:55:00.448567627Z",
    "properties" : {
      "projectName" : "Chips Project",
      "serverPort" : 8081,
      "baseName" : "gradleapp",
      "packageName" : "tech.jhipster.gradleapp",
      "jwtBase64Secret" : "NmE2NDhmMmQ5OWQzYzk4NmE4NjNlMmQzNmU3ZTU4ZDY2MmUxOWEwZGI4YTk4NDY0MTk4MmQyMWZlNDNlM2FjYg==",
      "date" : "2021-12-03T10:15:30.00Z",
      "kafkaClusterId" : "7870e9ec-dd1f-4562-86a2-df2199d5db1a",
      "springConfigurationFormat" : "yaml"
    }
  }, {
    "module" : "checkstyle",
    "date" : "2024-05-03T14:55:00.562838508Z",
    "properties" : {
      "projectName" : "Chips Project",
      "serverPort" : 8081,
      "baseName" : "gradleapp",
      "packageName" : "tech.jhipster.gradleapp",
      "jwtBase64Secret" : "NmE2NDhmMmQ5OWQzYzk4NmE4NjNlMmQzNmU3ZTU4ZDY2MmUxOWEwZGI4YTk4NDY0MTk4MmQyMWZlNDNlM2FjYg==",
      "date" : "2021-12-03T10:15:30.00Z",
      "kafkaClusterId" : "7870e9ec-dd1f-4562-86a2-df2199d5db1a",
      "springConfigurationFormat" : "yaml"
    }
  }, {
    "module" : "approval-tests",
    "date" : "2024-05-03T14:55:00.654501573Z",
    "properties" : {
      "projectName" : "Chips Project",
      "serverPort" : 8081,
      "baseName" : "gradleapp",
      "packageName" : "tech.jhipster.gradleapp",
      "jwtBase64Secret" : "NmE2NDhmMmQ5OWQzYzk4NmE4NjNlMmQzNmU3ZTU4ZDY2MmUxOWEwZGI4YTk4NDY0MTk4MmQyMWZlNDNlM2FjYg==",
      "date" : "2021-12-03T10:15:30.00Z",
      "kafkaClusterId" : "7870e9ec-dd1f-4562-86a2-df2199d5db1a",
      "springConfigurationFormat" : "yaml"
    }
  }, {
    "module" : "jqwik",
    "date" : "2024-05-03T14:55:00.741755635Z",
    "properties" : {
      "projectName" : "Chips Project",
      "serverPort" : 8081,
      "baseName" : "gradleapp",
      "packageName" : "tech.jhipster.gradleapp",
      "jwtBase64Secret" : "NmE2NDhmMmQ5OWQzYzk4NmE4NjNlMmQzNmU3ZTU4ZDY2MmUxOWEwZGI4YTk4NDY0MTk4MmQyMWZlNDNlM2FjYg==",
      "date" : "2021-12-03T10:15:30.00Z",
      "kafkaClusterId" : "7870e9ec-dd1f-4562-86a2-df2199d5db1a",
      "springConfigurationFormat" : "yaml"
    }
  } ]
}